odoo/addons/l10n_it_delivery_note_batch/README.rst
odoo/addons/l10n_it_delivery_note_batch/__init__.py
odoo/addons/l10n_it_delivery_note_batch/__manifest__.py
odoo/addons/l10n_it_delivery_note_batch/i18n/it.po
odoo/addons/l10n_it_delivery_note_batch/i18n/l10n_it_delivery_note_batch.pot
odoo/addons/l10n_it_delivery_note_batch/models/__init__.py
odoo/addons/l10n_it_delivery_note_batch/models/stock_delivery_note.py
odoo/addons/l10n_it_delivery_note_batch/models/stock_picking_batch.py
odoo/addons/l10n_it_delivery_note_batch/readme/CONTRIBUTORS.rst
odoo/addons/l10n_it_delivery_note_batch/readme/DESCRIPTION.rst
odoo/addons/l10n_it_delivery_note_batch/readme/USAGE.rst
odoo/addons/l10n_it_delivery_note_batch/static/description/icon.png
odoo/addons/l10n_it_delivery_note_batch/static/description/index.html
odoo/addons/l10n_it_delivery_note_batch/views/stock_picking_batch_views.xml
odoo12_addon_l10n_it_delivery_note_batch-12.0.1.0.0.99.dev7.dist-info/METADATA
odoo12_addon_l10n_it_delivery_note_batch-12.0.1.0.0.99.dev7.dist-info/WHEEL
odoo12_addon_l10n_it_delivery_note_batch-12.0.1.0.0.99.dev7.dist-info/top_level.txt
odoo12_addon_l10n_it_delivery_note_batch-12.0.1.0.0.99.dev7.dist-info/RECORD
