Metadata-Version: 2.1
Name: odoo12-addon-l10n-it-delivery-note-batch
Version: 12.0.1.0.0.99.dev7
Summary: Crea i DDT partendo da gruppi di prelievi
Home-page: https://github.com/OCA/l10n-italy/tree/12.0/l10n_it_delivery_note_batch
Author: Marco Colombo, Odoo Community Association (OCA)
Author-email: support@odoo-community.org
License: AGPL-3
Platform: UNKNOWN
Classifier: Programming Language :: Python
Classifier: Framework :: Odoo
Classifier: Framework :: Odoo :: 12.0
Classifier: License :: OSI Approved :: GNU Affero General Public License v3
Requires-Python: >=3.5
Requires-Dist: odoo12-addon-l10n-it-delivery-note
Requires-Dist: odoo <12.1dev,>=12.0a
